<?xml version="1.0" encoding="UTF-8"?>
<?oxygen RNGSchema="shared/cpf.rng" type="xml"?> <eac-cpf xmlns="urn:isbn:1-931666-33-4" xmlns:xlink="http://www.w3.org/1999/xlink" xmlns:xsi="http://www.w3.org/2001/XMLSchema-instance" xsi:schemaLocation="urn:isbn:1-931666-33-4 http://eac.staatsbibliothek-berlin.de/schema/cpf.xsd">
<control>
<recordId>QE00718</recordId>
<maintenanceStatus>revised</maintenanceStatus>
<maintenanceAgency>
<agencyCode>AU-VU:FCQD</agencyCode>
<agencyName>Find &amp; Connect - Queensland</agencyName>
<descriptiveNote>
<p></p>
</descriptiveNote>
</maintenanceAgency>
<languageDeclaration>
<language languageCode="eng">English</language>
<script scriptCode="Latn">Latin</script>
</languageDeclaration>
<conventionDeclaration>
<abbreviation>AACR2</abbreviation>
<citation>Anglo-American Cataloguing Rules</citation>
</conventionDeclaration>
<localControl localType="typeOfEntity">
<term>Archival Collection</term>
</localControl>
<maintenanceHistory>
<maintenanceEvent>
<eventType>created</eventType>
<eventDateTime standardDateTime="2013-11-14">2013-11-14</eventDateTime>
<agentType>human</agentType>
<agent>Jackie Bettington and Elizabeth Daniels</agent>
<eventDescription></eventDescription>
</maintenanceEvent>
<maintenanceEvent>
<eventType>updated</eventType>
<eventDateTime standardDateTime="2016-07-27">2016-07-27</eventDateTime>
<agentType>human</agentType>
<agent></agent>
<eventDescription></eventDescription>
</maintenanceEvent>
</maintenanceHistory>
</control>
<cpfDescription>
<identity><entityId>http://www.findandconnect.gov.au/ref/qld/biogs/QE00718b.htm</entityId>
<entityType>concept</entityType>
<nameEntry><part>Silky Oaks Haven for Children, Records</part>
<authorizedForm>AACR2</authorizedForm>
</nameEntry>
</identity>
<description><existDates>
<dateRange>
<fromDate standardDate="1940-01-01">1940</fromDate>
</dateRange>
</existDates>
<places>
</places>
<biogHist>
<abstract>The Silky Oaks Haven for Children describes its collection of records as containing:
'Personal information regarding entry and discharge dates, birth dates, parent and sibling names, school history, photographs of the site and accommodation, some contain records of the reasons for discharge. Photographs of the buildings and area show the location and accommodation of the client group, group photos help identify themselves, and other children and staff they may have shared time with.</abstract>
<h4>Access Conditions</h4>
<p>Documentation has been kept from 1940 onwards. However, information on residents in the early years is sparse. All past and present residents can have access to their files and the information therein. In cases where there are reports from professionals (eg psychologist), permission is first sought from the professional to release this information.</p>
<p>Persons wishing to view their file may need to establish their identity before access is granted. Once this is established, a mutually suitable time to view the material is made.</p>
<h4>Records</h4>
<p>The records of Silky Oaks Haven for Children have been organised into thirteen archival series. Some of these Series have more detail than others. Details about archival series are often added over an extended period of time as the archival collection they belong to is used, understood in light of new events or knowledge and documented by different people.</p>
<p>The series in this collection with extra detail are listed below:</p>
<list><item>Series 1: Client Files (1940 - 1991)</item>
<item>Series 2: Admission and Discharge Registers (11 December 1948 - 1990's) </item>
<item>Series 3: Minutes (1940 - Current) </item>
<item>Series 4: Annual Reports (13 October 1941 - 31 December 1998) </item>
<item>Series 8: Client Files - correspondence with State Government Departments (8 June 1940 - c. 31 December 1976 ) </item>
<item>Series 10: Client Files - Commonwealth Government Departments<br />
(c.1 January 1980 - c.31 December 1995) </item>
<item>Series 11: Weekly Returns (9cJuly 1957 - 17 June 1998) </item>
<item>Series 12: Admissions and Discharges - Correspondence and Forms (22 February 1947 - c.30 December 1961) </item></list>
<p>The remaining five series are:</p>
<list><item>Series 5: Newsletters</item>
<item>Series 6: Staff Reports to Council</item>
<item>Series 7: Minutes of Staff Meetings</item>
<item>Series 9: Donor Files - donated goods</item>
<item>Series 13: List of clients, staff and volunteers</item></list>

</biogHist>
</description>
<relations><cpfRelation cpfRelationType="associative" xlink:type="simple" xlink:href="http://www.findandconnect.gov.au/ref/qld/biogs/QE00160b.htm">
<relationEntry localType="Organisation">
Silky Oaks Haven for Children (1940 - )
</relationEntry>
</cpfRelation>
<cpfRelation cpfRelationType="associative" xlink:type="simple" xlink:href="http://www.findandconnect.gov.au/ref/qld/biogs/QE00725b.htm">
<relationEntry localType="Archival Series">
Client Files - Commonwealth Government Departments (c. 1980 - c. 1995)
</relationEntry>
</cpfRelation>
<cpfRelation cpfRelationType="associative" xlink:type="simple" xlink:href="http://www.findandconnect.gov.au/ref/qld/biogs/QE00720b.htm">
<relationEntry localType="Archival Series">
Client Files, Silky Oaks Haven for Children (1940 - 1991)
</relationEntry>
</cpfRelation>
<cpfRelation cpfRelationType="associative" xlink:type="simple" xlink:href="http://www.findandconnect.gov.au/ref/qld/biogs/QE00721b.htm">
<relationEntry localType="Archival Series">
Admission and Discharge Registers, Silky Oaks Haven for Children (1948 - c. 1990)
</relationEntry>
</cpfRelation>
<cpfRelation cpfRelationType="associative" xlink:type="simple" xlink:href="http://www.findandconnect.gov.au/ref/qld/biogs/QE00722b.htm">
<relationEntry localType="Archival Series">
Minutes, Silky Oaks Haven for Children (1940 - )
</relationEntry>
</cpfRelation>
<cpfRelation cpfRelationType="associative" xlink:type="simple" xlink:href="http://www.findandconnect.gov.au/ref/qld/biogs/QE00724b.htm">
<relationEntry localType="Archival Series">
Client Files - correspondence with State Government Departments (1940 - c. 1976)
</relationEntry>
</cpfRelation>
<cpfRelation cpfRelationType="associative" xlink:type="simple" xlink:href="http://www.findandconnect.gov.au/ref/qld/biogs/QE00726b.htm">
<relationEntry localType="Archival Series">
Weekly Returns (1957 - 1998)
</relationEntry>
</cpfRelation>
<cpfRelation cpfRelationType="associative" xlink:type="simple" xlink:href="http://www.findandconnect.gov.au/ref/qld/biogs/QE00727b.htm">
<relationEntry localType="Archival Series">
Admissions and Discharges - Correspondence and Forms (1947 - c. 1961)
</relationEntry>
</cpfRelation>
<cpfRelation cpfRelationType="associative" xlink:type="simple" xlink:href="http://www.findandconnect.gov.au/ref/qld/biogs/QE00723b.htm">
<relationEntry localType="Archival Series">
Annual Reports, Silky Oaks Haven for Children (1941 - 1998)
</relationEntry>
</cpfRelation>
<cpfRelation cpfRelationType="associative" xlink:type="simple" xlink:href="http://www.findandconnect.gov.au/ref/qld/biogs/QE00901b.htm">
<relationEntry localType="Organisation">
Grey Cottage (1960 - 1991)
</relationEntry>
<descriptiveNote>
<p>The records for Grey Cottage are held with the Silky Oaks Haven for Children records.</p>
</descriptiveNote>
</cpfRelation>
<cpfRelation cpfRelationType="associative" xlink:type="simple" xlink:href="http://www.findandconnect.gov.au/ref/qld/biogs/QE00897b.htm">
<relationEntry localType="Organisation">
Balmoral Cottage (1977 - 1993)
</relationEntry>
<descriptiveNote>
<p>Records for Balmoral Cottage are held with the Silky Oaks Haven for Children records.</p>
</descriptiveNote>
</cpfRelation>
<cpfRelation cpfRelationType="associative" xlink:type="simple" xlink:href="http://www.findandconnect.gov.au/ref/qld/biogs/QE00902b.htm">
<relationEntry localType="Organisation">
Alexander Cottage (1991 - )
</relationEntry>
<descriptiveNote>
<p>The records for Alexander Cottage are held with the Silky Oaks Haven for Children records.</p>
</descriptiveNote>
</cpfRelation>
<cpfRelation cpfRelationType="associative" xlink:type="simple" xlink:href="http://www.findandconnect.gov.au/ref/qld/biogs/QE00898b.htm">
<relationEntry localType="Organisation">
Bay Cottage (1970 - 1998)
</relationEntry>
<descriptiveNote>
<p>Records for Bay Cottage are held with the Silky Oaks Haven for Children records.</p>
</descriptiveNote>
</cpfRelation>
<cpfRelation cpfRelationType="associative" xlink:type="simple" xlink:href="http://www.findandconnect.gov.au/ref/qld/biogs/QE00899b.htm">
<relationEntry localType="Organisation">
Durak Cottage (1981 - 1993)
</relationEntry>
<descriptiveNote>
<p>The records for Durak Cottage are held with the Silky Oaks Haven for Children records.</p>
</descriptiveNote>
</cpfRelation>
<cpfRelation cpfRelationType="associative" xlink:type="simple" xlink:href="http://www.findandconnect.gov.au/ref/qld/biogs/QE00900b.htm">
<relationEntry localType="Organisation">
Farm Cottage (1965 - 1989)
</relationEntry>
<descriptiveNote>
<p>Records for Farm Cottage are held with the Silky Oaks Haven for Children records.</p>
</descriptiveNote>
</cpfRelation>
<cpfRelation cpfRelationType="associative" xlink:type="simple" xlink:href="http://www.findandconnect.gov.au/ref/qld/biogs/QE00719b.htm">
<relationEntry localType="Contact Details">
Silky Oaks Haven for Children - Contact Details
</relationEntry>
</cpfRelation>
<resourceRelation resourceRelationType="subjectOf">
<relationEntry localType="published">'Silky Oaks Haven for Children, Records', in <span style="font-style:italic">Find &amp; Connect - Queensland</span>, </relationEntry>

<objectXMLWrap>
<bibref xmlns="urn:isbn:1-931666-22-9">
<title render="italic">Silky Oaks Haven for Children, Records</title>
<bibseries>
<title render="italic">Find &amp; Connect - Queensland</title>
</bibseries>
<extptr linktype="simple" href="http://www.findandconnect.gov.au/ref/qld/biogs/QE00718b.htm"></extptr>
</bibref>
</objectXMLWrap>
</resourceRelation>
</relations>
</cpfDescription>
</eac-cpf>