<?xml version="1.0" encoding="UTF-8"?>
<?oxygen RNGSchema="shared/cpf.rng" type="xml"?>
<eac-cpf xmlns="urn:isbn:1-931666-33-4" xmlns:xlink="http://www.w3.org/1999/xlink" xmlns:xsi="http://www.w3.org/2001/XMLSchema-instance" xsi:schemaLocation="urn:isbn:1-931666-33-4 http://eac.staatsbibliothek-berlin.de/schema/cpf.xsd">
<control>
<recordId>SE00069</recordId>
<maintenanceStatus>revised</maintenanceStatus>
<maintenanceAgency>
<agencyCode>AU-VU:FCSA</agencyCode>
<agencyName>Find &amp; Connect - South Australia</agencyName>
<descriptiveNote>
<p></p>
</descriptiveNote>
</maintenanceAgency>
<languageDeclaration>
<language languageCode="eng">English</language>
<script scriptCode="Latn">Latin</script>
</languageDeclaration>
<conventionDeclaration>
<abbreviation>AACR2</abbreviation>
<citation>Anglo-American Cataloguing Rules</citation>
</conventionDeclaration>
<localControl localType="typeOfEntity">
<term>Organisation</term>
</localControl>
<maintenanceHistory>
<maintenanceEvent>
<eventType>created</eventType>
<eventDateTime standardDateTime="2011-02-09">2011-02-09</eventDateTime>
<agentType>human</agentType>
<agent>Karen George and Gary George</agent>
<eventDescription></eventDescription>
</maintenanceEvent>
<maintenanceEvent>
<eventType>updated</eventType>
<eventDateTime standardDateTime="2017-08-31">2017-08-31</eventDateTime>
<agentType>human</agentType>
<agent></agent>
<eventDescription></eventDescription>
</maintenanceEvent>
</maintenanceHistory>
</control>
<cpfDescription>
<identity><entityId>http://www.findandconnect.gov.au/ref/sa/biogs/SE00069b.htm</entityId>
<entityType>corporateBody</entityType>
<nameEntry><part>Ilfracombe, Boys Reformatory</part>
<authorizedForm>AACR2</authorizedForm>
</nameEntry>
</identity>
<description><existDates>
<dateRange>
<fromDate standardDate="1869-01-01">1869</fromDate>
<toDate standardDate="1880-12-31">1880</toDate>
</dateRange>
</existDates>
<places>
</places>
<functions>
<function>
<term>Reformatory</term>
</function>
<function>
<term>Government-run</term>
</function>
<function>
<term>Home</term>
</function>
</functions>
<biogHist>
<abstract>Ilfracombe Boys Reformatory opened in Burnside in 1869. Run by the government it took in a number of boys convicted of offences who had been accommodated in the Grace Darling Hotel, Brighton. Other boys were sent to the Boys Reformatory, Magill. Ilfracombe closed in 1880 when the boys from both reformatories were moved to the Reformatory Hulk, the Fitzjames.</abstract>
<p>In 1866 the majority of children were moved out of the Destitute Asylum as a result of the passing of the new Destitute Persons Relief Act. Boys who had been convicted of offences were among the large group of children relocated briefly to the Exhibition Building on North Terrace and then to the Grace Darling Hotel at Brighton.</p>
<p>Due to overcrowding and pervading illness at the Hotel, however, all children there were moved to other institutions. In December 1869, a number of the boys were moved to a former mansion in Burnside known as Ilfracombe. The remainder went to the new Boys Reformatory at Magill.</p>
<p>In its 1869 report, the Destitute Board commented on conditions at Ilfracombe. It also stated that the boys were involved in shoemaking, stone-breaking, road-building shed building and gardening. The report also explained that:</p>
<p>'The building itself, which in some parts was dilapidated, has been, by several of the boys, with the help of the master, repaired, plastered.'</p>
<p>A newspaper article the following year commended the work the boys had done to the old building noting that:</p>
<p>'The whole of the improvements necessary to transform a private residence into a Reformatory Institution are being carried out by the boys themselves without any external mechanical assistance whatever. '</p>
<p>Rosamond and Florence Hill, English sisters who visited Ilfracombe in 1873, commented on the rough living conditions under which the 25 boys were living. However, they were impressed with the boys themselves whom they described as appearing healthy and happy. The boys attended school for two hours each day and were kept occupied at other times with caring for cows and pigs, making shoes and straw covers for wine bottles.</p>
<p>Ilfracombe continued to operate as a Boys Reformatory until 1880 when the boys from there and those from the Boys' Reformatory, Magill, were transferred to the Reformatory Hulk, the Fitzjames.</p>
<chronList><chronItem>
<dateRange><fromDate standardDate="1869-01-01">1869</fromDate>
<toDate standardDate="1880-12-31">1880</toDate>
</dateRange>
<placeEntry>Burnside</placeEntry>
<event>Location - Ilfracombe Boys Reformatory was situated at Burnside</event>
</chronItem>
</chronList>

</biogHist>
</description>
<relations><cpfRelation cpfRelationType="associative" xlink:type="simple" xlink:href="http://www.findandconnect.gov.au/ref/sa/biogs/SE00063b.htm">
<relationEntry localType="Organisation">
Destitute Board, South Australian Government (1849 - 1886)
</relationEntry>
<dateRange>
<fromDate standardDate="1869-01-01">1869</fromDate>
<toDate standardDate="1880-12-31">1880</toDate>
</dateRange>
</cpfRelation>
<cpfRelation cpfRelationType="associative" xlink:type="simple" xlink:href="http://www.findandconnect.gov.au/ref/sa/biogs/SE00743b.htm">
<relationEntry localType="Archival Collection">
Records created by the Destitute Board (c. 1845 - 1927)
</relationEntry>
</cpfRelation>
<cpfRelation cpfRelationType="associative" xlink:type="simple" xlink:href="http://www.findandconnect.gov.au/ref/sa/biogs/SE00551b.htm">
<relationEntry localType="Archival Series">
Minutes - Destitute Board (1849 - 1927)
</relationEntry>
<descriptiveNote>
<p>Held by State Records of SA. These minutes give brief details of cases and general business considered by the Destitute Board. They may include information related to Illfracombe.</p>
</descriptiveNote>
</cpfRelation>
<cpfRelation cpfRelationType="associative" xlink:type="simple" xlink:href="http://www.findandconnect.gov.au/ref/sa/biogs/SE00359b.htm">
<relationEntry localType="Legislation">
Destitute Persons Relief Act 1866 (1867 - 1872)
</relationEntry>
</cpfRelation>
<cpfRelation cpfRelationType="associative" xlink:type="simple" xlink:href="http://www.findandconnect.gov.au/ref/sa/biogs/SE01217b.htm">
<relationEntry localType="Organisation">
Boys' Reformatory, Magill (1869 - 1880)
</relationEntry>
<descriptiveNote>
<p>Boys from the Boys' Reformatory, Magill and Ilfracombe Boys' Reformatory were sent to the Reformatory Hulk, Fitzjames in 1880.</p>
</descriptiveNote>
</cpfRelation>
<cpfRelation cpfRelationType="associative" xlink:type="simple" xlink:href="http://www.findandconnect.gov.au/ref/sa/biogs/SE00068b.htm">
<relationEntry localType="Organisation">
Brighton Industrial School (1867 - 1869)
</relationEntry>
<dateRange>
<fromDate standardDate="1869-12-01">December 1869</fromDate>
</dateRange>
<descriptiveNote>
<p>Due to overcrowding, boys from the Brighton Industrial School were moved to Ilfracombe Boys Reformatory.</p>
</descriptiveNote>
</cpfRelation>
<cpfRelation cpfRelationType="temporal-later" xlink:type="simple" xlink:href="http://www.findandconnect.gov.au/ref/sa/biogs/SE00056b.htm">
<relationEntry localType="Organisation">
Boys' Reformatory Hulk, Fitzjames (1880 - 1891)
</relationEntry>
<descriptiveNote>
<p>In 1880 boys were transferred from Ilfracombe Boys Reformatory to the Boys Reformatory Hulk, Fitzjames</p>
</descriptiveNote>
</cpfRelation>
<resourceRelation resourceRelationType="subjectOf">
<relationEntry localType="published">'Ilfracombe, Boys Reformatory', in <span style="font-style:italic">Find &amp; Connect - South Australia</span>, </relationEntry>

<objectXMLWrap>
<bibref xmlns="urn:isbn:1-931666-22-9">
<title render="italic">Ilfracombe, Boys Reformatory</title>
<bibseries>
<title render="italic">Find &amp; Connect - South Australia</title>
</bibseries>
<extptr linktype="simple" href="http://www.findandconnect.gov.au/ref/sa/biogs/SE00069b.htm"></extptr>
</bibref>
</objectXMLWrap>
</resourceRelation>
<resourceRelation resourceRelationType="other" xlink:type="simple" xlink:href="http://www.findandconnect.gov.au/ref/sa/bib/SP0000254.htm">
<relationEntry localType="published">Newspaper Article: No title</relationEntry>

<objectXMLWrap>
<bibref xmlns="urn:isbn:1-931666-22-9">
<name type="author"></name>
<title render="quoted">No title</title>
<imprint>
<place>Adelaide, South Australia</place>
<date>1870</date>
</imprint>
<bibseries>
<title render="italic">South Australian Register</title>
<num type="pages">5</num>
</bibseries>
<extptr linktype="simple" href="http://nla.gov.au/nla.news-article39205941"></extptr>
</bibref>
</objectXMLWrap>

<descriptiveNote>
<p>Source used to compile entry</p>
</descriptiveNote>
</resourceRelation>
<resourceRelation resourceRelationType="other" xlink:type="simple" xlink:href="http://www.findandconnect.gov.au/ref/sa/bib/SP0000253.htm">
<relationEntry localType="published">Newspaper Article: DESTITUTION IN 1869</relationEntry>

<objectXMLWrap>
<bibref xmlns="urn:isbn:1-931666-22-9">
<name type="author"></name>
<title render="quoted">DESTITUTION IN 1869</title>
<imprint>
<place>Adelaide, South Australia</place>
<date>1870</date>
</imprint>
<bibseries>
<title render="italic">South Australian Register</title>
<num type="pages">2</num>
</bibseries>
<extptr linktype="simple" href="http://nla.gov.au/nla.news-article39201829"></extptr>
</bibref>
</objectXMLWrap>

<descriptiveNote>
<p>Source used to compile entry</p>
</descriptiveNote>
</resourceRelation>
<resourceRelation resourceRelationType="other" xlink:type="simple" xlink:href="http://www.findandconnect.gov.au/ref/sa/bib/SP0000042.htm">
<relationEntry localType="published">Resource: Finding your own way</relationEntry>

<objectXMLWrap>
<bibref xmlns="urn:isbn:1-931666-22-9">
<name type="author">George, Karen</name>
<title render="italic">Finding your own way</title>
<imprint>
<publisher>Nunkuwarrin Yunti of South Australia Inc.</publisher>
<date>2005</date>
</imprint>
<extptr linktype="simple" href="http://nunku.org.au/resources/"></extptr>
</bibref>
</objectXMLWrap>

<descriptiveNote>
<p>Source used to compile entry</p>
</descriptiveNote>
</resourceRelation>
<resourceRelation resourceRelationType="other" xlink:type="simple" xlink:href="http://www.findandconnect.gov.au/ref/sa/bib/SP0000012.htm">
<relationEntry localType="published">Book: Rations, Residence, Resources: A history of social welfare in South Australia since 1836</relationEntry>

<objectXMLWrap>
<bibref xmlns="urn:isbn:1-931666-22-9">
<name type="author">Dickey, Brian</name>
<title render="italic">Rations, Residence, Resources: A history of social welfare in South Australia since 1836</title>
<imprint>
<place>Adelaide</place>
<publisher>Wakefield Press</publisher>
<date>1986</date>
</imprint>
</bibref>
</objectXMLWrap>

</resourceRelation>
<resourceRelation resourceRelationType="other" xlink:type="simple" xlink:href="http://www.findandconnect.gov.au/ref/sa/objects/SD0000384.htm">
<relationEntry localType="digitalObject">Stonyfell wine label</relationEntry>

<objectXMLWrap>
<archref xmlns="urn:isbn:1-931666-22-9">
<repository>'File on the property Ilfracombe: 1847-1943 [Local History], Burnside Library</repository>
<unittitle>Stonyfell wine label</unittitle>
<unitdate>1980?</unitdate>
</archref>
</objectXMLWrap>

</resourceRelation>
<resourceRelation resourceRelationType="other" xlink:type="simple" xlink:href="http://www.findandconnect.gov.au/ref/sa/objects/SD0000383.htm">
<relationEntry localType="digitalObject">Ilfracombe Boys' Reformatory</relationEntry>

<objectXMLWrap>
<archref xmlns="urn:isbn:1-931666-22-9">
<repository>Gunton Eric, <span style="font-style:italic">Gracious homes of colonial Adelaide</span>, 1983.</repository>
<unittitle>Ilfracombe Boys' Reformatory</unittitle>
</archref>
</objectXMLWrap>

<descriptiveNote>
<p>Include in Gallery</p>
</descriptiveNote>
</resourceRelation>
<resourceRelation resourceRelationType="other" xlink:type="simple" xlink:href="http://www.findandconnect.gov.au/ref/sa/objects/SD0000382.htm">
<relationEntry localType="digitalObject">Ilfracombe, facing north</relationEntry>

<objectXMLWrap>
<archref xmlns="urn:isbn:1-931666-22-9">
<repository>'File on the property Ilfracombe: 1847-1943 [Local History], Burnside Library</repository>
<unittitle>Ilfracombe, facing north</unittitle>
<unitdate>c. 1847</unitdate>
<abstract>Caption (written on back of photograph): Ilfracombe, Facing North - Mrs Gee with her poodle Fifi - Original lent by Mrs R Jenkins, Kensington - Ilfracombe was built by Dr. Nash, first Colonial Surgeon. c.1847</abstract>
</archref>
</objectXMLWrap>

<descriptiveNote>
<p>Include in Gallery</p>
</descriptiveNote>
</resourceRelation>
</relations>
</cpfDescription>
</eac-cpf>