<?xml version="1.0" encoding="UTF-8"?>
<?oxygen RNGSchema="shared/cpf.rng" type="xml"?>
<eac-cpf xmlns="urn:isbn:1-931666-33-4" xmlns:xlink="http://www.w3.org/1999/xlink" xmlns:xsi="http://www.w3.org/2001/XMLSchema-instance" xsi:schemaLocation="urn:isbn:1-931666-33-4 http://eac.staatsbibliothek-berlin.de/schema/cpf.xsd">
<control>
<recordId>NE01087</recordId>
<maintenanceStatus>revised</maintenanceStatus>
<maintenanceAgency>
<agencyCode>AU-VU:FCNS</agencyCode>
<agencyName>Find &amp; Connect - New South Wales</agencyName>
<descriptiveNote>
<p></p>
</descriptiveNote>
</maintenanceAgency>
<languageDeclaration>
<language languageCode="eng">English</language>
<script scriptCode="Latn">Latin</script>
</languageDeclaration>
<conventionDeclaration>
<abbreviation>AACR2</abbreviation>
<citation>Anglo-American Cataloguing Rules</citation>
</conventionDeclaration>
<localControl localType="typeOfEntity">
<term>Archival Series</term>
</localControl>
<maintenanceHistory>
<maintenanceEvent>
<eventType>created</eventType>
<eventDateTime standardDateTime="2012-02-20">2012-02-20</eventDateTime>
<agentType>human</agentType>
<agent>Melissa Downing</agent>
<eventDescription></eventDescription>
</maintenanceEvent>
<maintenanceEvent>
<eventType>updated</eventType>
<eventDateTime standardDateTime="2017-03-15">2017-03-15</eventDateTime>
<agentType>human</agentType>
<agent></agent>
<eventDescription></eventDescription>
</maintenanceEvent>
</maintenanceHistory>
</control>
<cpfDescription>
<identity><entityId>http://www.findandconnect.gov.au/ref/nsw/biogs/NE01087b.htm</entityId>
<entityId localType="State Records Authority of New South Wales Series Number">13362</entityId>
<entityType>concept</entityType>
<nameEntry><part>Registers of Inmates</part>
<part localType="parent">Randwick Asylum for Destitute Children</part>
<authorizedForm>AACR2</authorizedForm>
</nameEntry>
</identity>
<description><existDates>
<dateRange>
<fromDate standardDate="1852-06-01">June 1852</fromDate>
<toDate standardDate="1915-08-31">August 1915</toDate>
</dateRange>
</existDates>
<places>
</places>
<biogHist>
<abstract>The Registers of Inmates record details of children admitted into the asylums managed by the Society for the Relief of Destitute Children. The information in the registers varies. The earlier entries, from the 19th century, record: name and age of child; date of admission; religion of parents; reason for admission; and discharge details including date, child's age, and to whom discharged (e.g. parents, apprenticed out, deceased, etc). The entries for the twentieth century record: name, age and religion of child; date of admission and discharge; whether vaccinated or not; whether baptised or not; and details of discharge (e.g. where and to whom discharged, age, etc.).</abstract>
<h4>Access Conditions</h4>
<p>Open access.</p>
<h4>Records</h4>
<p>These volumes are indexed. Copies of the indexes are available in the search rooms of the State Records Authority of New South Wales and should be consulted before using the registers.</p>

</biogHist>
</description>
<relations><cpfRelation cpfRelationType="associative" xlink:type="simple" xlink:href="http://www.findandconnect.gov.au/ref/nsw/biogs/NE01638b.htm">
<relationEntry localType="Archival Collection">
New South Wales State Archives Collection (1788 - )
</relationEntry>
</cpfRelation>
<cpfRelation cpfRelationType="associative" xlink:type="simple" xlink:href="http://www.findandconnect.gov.au/ref/nsw/biogs/NE00498b.htm">
<relationEntry localType="Organisation">
Asylum for Destitute Children (1852 - 1858)
</relationEntry>
</cpfRelation>
<cpfRelation cpfRelationType="associative" xlink:type="simple" xlink:href="http://www.findandconnect.gov.au/ref/nsw/biogs/NE00497b.htm">
<relationEntry localType="Organisation">
Randwick Asylum for Destitute Children (1858 - 1915)
</relationEntry>
</cpfRelation>
<cpfRelation cpfRelationType="associative" xlink:type="simple" xlink:href="http://www.findandconnect.gov.au/ref/nsw/biogs/NE01378b.htm">
<relationEntry localType="Organisation">
Society for the Relief of Destitute Children (1852 - c. 1915)
</relationEntry>
</cpfRelation>
<cpfRelation cpfRelationType="associative" xlink:type="simple" xlink:href="http://www.findandconnect.gov.au/ref/nsw/biogs/NE01466b.htm">
<relationEntry localType="Contact Details">
State Records Authority of New South Wales - Contact Details
</relationEntry>
</cpfRelation>
<resourceRelation resourceRelationType="subjectOf">
<relationEntry localType="published">'Registers of Inmates', in <span style="font-style:italic">Find &amp; Connect - New South Wales</span>, </relationEntry>

<objectXMLWrap>
<bibref xmlns="urn:isbn:1-931666-22-9">
<title render="italic">Registers of Inmates</title>
<bibseries>
<title render="italic">Find &amp; Connect - New South Wales</title>
</bibseries>
<extptr linktype="simple" href="http://www.findandconnect.gov.au/ref/nsw/biogs/NE01087b.htm"></extptr>
</bibref>
</objectXMLWrap>
</resourceRelation>
<resourceRelation resourceRelationType="other" xlink:type="simple" xlink:href="http://www.findandconnect.gov.au/ref/nsw/bib/NP0000459.htm">
<relationEntry localType="published">Resource Section: Index to Child Care and Protection</relationEntry>

<objectXMLWrap>
<bibref xmlns="urn:isbn:1-931666-22-9">
<name type="author"></name>
<title render="quoted">Index to Child Care and Protection</title>
<imprint>
<publisher>State of New South Wales through the State Records Authority of NSW 2016</publisher>
</imprint>
<bibseries>
<title render="italic">State Records Authority of New South Wales website</title>
</bibseries>
<extptr linktype="simple" href="https://www.records.nsw.gov.au/archives/collections-and-research/guides-and-indexes/child-care-and-protection-index"></extptr>
</bibref>
</objectXMLWrap>

</resourceRelation>
<resourceRelation resourceRelationType="other" xlink:type="simple" xlink:href="http://www.findandconnect.gov.au/ref/nsw/bib/NP0000678.htm">
<relationEntry localType="published">Resource Section: Randwick Asylum for Destitute Children</relationEntry>

<objectXMLWrap>
<bibref xmlns="urn:isbn:1-931666-22-9">
<name type="author"></name>
<title render="quoted">Randwick Asylum for Destitute Children</title>
<imprint>
<publisher>State of New South Wales through the State Records Authority of NSW 2016</publisher>
</imprint>
<bibseries>
<title render="italic">State Records Authority of New South Wales website</title>
</bibseries>
<extptr linktype="simple" href="https://www.records.nsw.gov.au/archives/collections-and-research/guides-and-indexes/randwick-asylum-destitute-children"></extptr>
</bibref>
</objectXMLWrap>

<descriptiveNote>
<p>Source used to compile entry</p>
</descriptiveNote>
</resourceRelation>
<resourceRelation resourceRelationType="other" xlink:type="simple" xlink:href="http://www.findandconnect.gov.au/ref/nsw/bib/NP0000001.htm">
<relationEntry localType="published">Resource: Connecting Kin: Guide to Records</relationEntry>

<objectXMLWrap>
<bibref xmlns="urn:isbn:1-931666-22-9">
<name type="author">Thinee, Kristy and Bradford, Tracy</name>
<title render="italic">Connecting Kin: Guide to Records</title>
<imprint>
<place>Sydney, New South Wales</place>
<publisher>New South Wales Department of Community Services</publisher>
<date>1998</date>
</imprint>
<extptr linktype="simple" href="http://www.community.nsw.gov.au/__data/assets/pdf_file/0008/319256/connectkin_guide.pdf"></extptr>
</bibref>
</objectXMLWrap>

<descriptiveNote>
<p>Source used to compile entry</p>
</descriptiveNote>
</resourceRelation>
</relations>
</cpfDescription>
</eac-cpf>